pellipop/Video.py
pellipop/__about__.py
pellipop/__init__.py
pellipop/cli.py
pellipop/gui.py
pellipop/main.py
pellipop/path_fixer.py
pellipop/pellipop.ico
pellipop/pip.py
pellipop/whisper_from_url.py
pellipop/speech_to_text/__init__.py
pellipop/speech_to_text/whisperMode.py
pellipop-0.9.3.dist-info/METADATA
pellipop-0.9.3.dist-info/WHEEL
pellipop-0.9.3.dist-info/entry_points.txt
pellipop-0.9.3.dist-info/licenses/LICENSE.txt
pellipop-0.9.3.dist-info/RECORD
