Metadata-Version: 2.4
Name: pellipop
Version: 0.9.3
Summary: A graphical and command-line tool to extract key frames from videos along with their retranscription. It uses the Whisper API to transcribe the audio. It also generates a CSV file with the extracted key frames and their corresponding text.
Project-URL: Homepage, https://github.com/CERES-Sorbonne/Pellipop
Project-URL: Documentation, https://github.com/CERES-Sorbonne/Pellipop#readme
Project-URL: Issues, https://github.com/CERES-Sorbonne/Pellipop/issues
Project-URL: Source, https://github.com/CERES-Sorbonne/Pellipop
Author: EdouardBoute
Author-email: Marceau-h <pypi@marceau-h.fr>, Orion Alié <someonefefe@gmail.com>
License-Expression: MPL-2.0
License-File: LICENSE.txt
Keywords: STT,frame,keyframes,panoptic,speech,speech-to-text,transcription,video
Classifier: Development Status :: 4 - Beta
Classifier: Intended Audience :: Developers
Classifier: Intended Audience :: End Users/Desktop
Classifier: Intended Audience :: Information Technology
Classifier: Intended Audience :: Science/Research
Classifier: License :: OSI Approved :: Mozilla Public License 2.0 (MPL 2.0)
Classifier: Operating System :: OS Independent
Classifier: Programming Language :: Python
Classifier: Programming Language :: Python :: 3 :: Only
Classifier: Programming Language :: Python :: 3.10
Classifier: Programming Language :: Python :: 3.11
Classifier: Programming Language :: Python :: 3.12
Classifier: Programming Language :: Python :: 3.13
Classifier: Programming Language :: Python :: Implementation :: CPython
Classifier: Programming Language :: Python :: Implementation :: PyPy
Requires-Python: >=3.10
Requires-Dist: ffmpeg
Requires-Dist: filedetect
Requires-Dist: requests~=2.31.0
Requires-Dist: tqdm
Requires-Dist: ttkbootstrap~=1.10.1
Requires-Dist: validators~=0.22.0
Requires-Dist: whisper-client~=0.4.0
